arkalos/__init__.py
arkalos/py.typed
arkalos/ai/__init__.py
arkalos/ai/actions/__init__.py
arkalos/ai/actions/ai_action.py
arkalos/ai/actions/search_dwh_action.py
arkalos/ai/actions/text_to_sql_action.py
arkalos/ai/actions/which_action.py
arkalos/ai/agents/__init__.py
arkalos/ai/agents/ai_agent.py
arkalos/ai/agents/dwh_agent.py
arkalos/ai/envs/ai_env.py
arkalos/ai/evals/evaluator.py
arkalos/ai/trainers/trainer.py
arkalos/browser/__init__.py
arkalos/browser/web_browser.py
arkalos/cli/__init__.py
arkalos/cli/init.py
arkalos/cli/make_mig.py
arkalos/cli/make_mig_dwh.py
arkalos/cli/make_mw.py
arkalos/cli/migrate.py
arkalos/cli/migrate_dwh.py
arkalos/cli/rollback.py
arkalos/cli/rollback_dwh.py
arkalos/cli/serve.py
arkalos/cli/common/make_migration_command.py
arkalos/core/app.py
arkalos/core/bootstrap.py
arkalos/core/config.py
arkalos/core/db.py
arkalos/core/dwh.py
arkalos/core/env.py
arkalos/core/http.py
arkalos/core/path.py
arkalos/core/registry.py
arkalos/core/logger/console_formatter.py
arkalos/core/logger/file_handler.py
arkalos/core/logger/format_exception.py
arkalos/core/logger/info_filter.py
arkalos/core/logger/json_formatter.py
arkalos/core/logger/log.py
arkalos/core/logger/log_level.py
arkalos/core/logger/logger.py
arkalos/data/analyzers/__init__.py
arkalos/data/analyzers/cluster/cluster_analyzer.py
arkalos/data/database/database.py
arkalos/data/extractors/__init__.py
arkalos/data/extractors/airtable_extractor.py
arkalos/data/extractors/data_extractor.py
arkalos/data/extractors/google_extractor.py
arkalos/data/extractors/notion_extractor.py
arkalos/data/extractors/web_extractor.py
arkalos/data/extractors/google/google_analytics.py
arkalos/data/extractors/google/google_drive.py
arkalos/data/transformers/__init__.py
arkalos/data/transformers/data_transformer.py
arkalos/data/visualizers/__init__.py
arkalos/data/visualizers/bar_chart.py
arkalos/data/visualizers/cluster_bar_chart.py
arkalos/data/visualizers/corr_heatmap.py
arkalos/data/visualizers/dendrogram.py
arkalos-0.7.0.dist-info/METADATA
arkalos-0.7.0.dist-info/WHEEL
arkalos-0.7.0.dist-info/entry_points.txt
arkalos-0.7.0.dist-info/licenses/LICENSE.md
arkalos-0.7.0.dist-info/RECORD
