Metadata-Version: 2.4
Name: arkalos
Version: 0.7.0
Summary: Arkalos is an easy-to-use framework for data analysis, building data apps, warehouses, AI agents, robots, ML, training LLMs with elegant syntax. It just works.
Project-URL: Homepage, https://arkalos.com
Project-URL: Documentation, https://arkalos.com
Project-URL: Repository, https://github.com/arkaloscom/arkalos
Project-URL: Issues, https://github.com/arkaloscom/arkalos/issues
Project-URL: Changelog, https://github.com/arkaloscom/arkalos/blob/main/CHANGELOG.md
Project-URL: Licesne, https://github.com/arkaloscom/arkalos/blob/main/LICENSE.md
Project-URL: Community, https://x.com/i/communities/1889982611667534002
Author: Mev-Rael
License-Expression: MIT
License-File: LICENSE.md
Keywords: agent,ai,airtable,api,etl,framework,ml,notion,sqlite,warehouse
Requires-Python: >=3.13
Requires-Dist: altair>=5.5.0
Requires-Dist: arrow>=1.3.0
Requires-Dist: beautifulsoup4>=4.13.3
Requires-Dist: datasets>=3.2.0
Requires-Dist: duckdb>=1.3.0
Requires-Dist: faker>=35.0.0
Requires-Dist: fastapi[standard]>=0.115.8
Requires-Dist: google-analytics-admin>=0.23.5
Requires-Dist: google-analytics-data>=0.18.17
Requires-Dist: google-api-python-client-stubs>=1.29.0
Requires-Dist: google-api-python-client>=2.160.0
Requires-Dist: google-auth-httplib2>=0.2.0
Requires-Dist: google-auth-oauthlib>=1.2.1
Requires-Dist: ibis-framework[duckdb,sqlite]>=10.5.0
Requires-Dist: kneed>=0.8.5
Requires-Dist: lxml>=5.3.1
Requires-Dist: markdownify>=1.1.0
Requires-Dist: matplotlib>=3.10.0
Requires-Dist: nltk>=3.9.1
Requires-Dist: numpy>=2.2.2
Requires-Dist: ollama>=0.4.7
Requires-Dist: openai>=1.76.0
Requires-Dist: pandas-stubs>=2.2.3.241126
Requires-Dist: pandas>=2.2.3
Requires-Dist: playwright>=1.51.0
Requires-Dist: polars>=1.20.0
Requires-Dist: pydantic>=2.10.6
Requires-Dist: pytest>=8.3.5
Requires-Dist: python-dotenv>=1.0.1
Requires-Dist: requests>=2.32.3
Requires-Dist: scikit-learn>=1.6.1
Requires-Dist: scipy-stubs>=1.15.3.0
Requires-Dist: scipy>=1.15.1
Requires-Dist: seaborn>=0.13.2
Requires-Dist: sqlglot>=26.20.0
Requires-Dist: tabulate>=0.9.0
Requires-Dist: types-requests>=2.32.0.20241016
Requires-Dist: vega-datasets>=0.9.0
